seeqc_client/API.md
seeqc_client/__init__.py
seeqc_client/authorisation.py
seeqc_client/black_logo.png
seeqc_client/connection.py
seeqc_client/plotting.py
seeqc_client/seeqc_client.py
seeqc_client/tests/__init__.py
seeqc_client/tests/mocked_routes.py
seeqc_client/tests/test_initialisation.py
seeqc_client/tests/test_routes.py
seeqc_client/tests/test_vars.py
tests/__init__.py
tests/mocked_routes.py
tests/test_initialisation.py
tests/test_routes.py
tests/test_vars.py
seeqc_client-0.10.1.dist-info/LICENSE
seeqc_client-0.10.1.dist-info/METADATA
seeqc_client-0.10.1.dist-info/WHEEL
seeqc_client-0.10.1.dist-info/top_level.txt
seeqc_client-0.10.1.dist-info/RECORD
