Metadata-Version: 2.2
Name: seeqc-client
Version: 0.10.1
Summary: Interface with Seeqc Cloud
Author: Seeqc
License:                     GNU GENERAL PUBLIC LICENSE
Project-URL: Homepage, https://github.com/seeqc/seeqc-client
Classifier: License :: OSI Approved :: GNU General Public License v3 or later (GPLv3+)
Classifier: Programming Language :: Python
Classifier: Programming Language :: Python :: 3
Requires-Python: >=3.8
License-File: LICENSE
Requires-Dist: requests>=2
Requires-Dist: werkzeug>=2
Requires-Dist: numpy>=1.21
Requires-Dist: matplotlib>=3
